{
	"configurations" : 
	[
		{
			"directories" : 
			[
				{
					"build" : ".",
					"hasInstallRule" : true,
					"jsonFile" : "directory-.-e50c6c5689865457dda7.json",
					"minimumCMakeVersion" : 
					{
						"string" : "3.12"
					},
					"projectIndex" : 0,
					"source" : ".",
					"targetIndexes" : 
					[
						0,
						1,
						2
					]
				}
			],
			"name" : "",
			"projects" : 
			[
				{
					"directoryIndexes" : 
					[
						0
					],
					"name" : "my_package",
					"targetIndexes" : 
					[
						0,
						1,
						2
					]
				}
			],
			"targets" : 
			[
				{
					"directoryIndex" : 0,
					"id" : "my_node::@6890427a1f51a3e7e1df",
					"jsonFile" : "target-my_node-18c4feaa03608de0f72e.json",
					"name" : "my_node",
					"projectIndex" : 0
				},
				{
					"directoryIndex" : 0,
					"id" : "my_package_uninstall::@6890427a1f51a3e7e1df",
					"jsonFile" : "target-my_package_uninstall-ab8e8b80629a1c43be27.json",
					"name" : "my_package_uninstall",
					"projectIndex" : 0
				},
				{
					"directoryIndex" : 0,
					"id" : "uninstall::@6890427a1f51a3e7e1df",
					"jsonFile" : "target-uninstall-7adcd85607ee999e8e0a.json",
					"name" : "uninstall",
					"projectIndex" : 0
				}
			]
		}
	],
	"kind" : "codemodel",
	"paths" : 
	{
		"build" : "/home/ziad/Ziad_WS/ROS2/code/build/my_package",
		"source" : "/home/ziad/Ziad_WS/ROS2/code/src/my_package"
	},
	"version" : 
	{
		"major" : 2,
		"minor" : 3
	}
}
